google/cloud/saasplatform_saasservicemgmt/__init__.py
google/cloud/saasplatform_saasservicemgmt/gapic_version.py
google/cloud/saasplatform_saasservicemgmt/py.typed
google/cloud/saasplatform_saasservicemgmt_v1beta1/__init__.py
google/cloud/saasplatform_saasservicemgmt_v1beta1/gapic_metadata.json
google/cloud/saasplatform_saasservicemgmt_v1beta1/gapic_version.py
google/cloud/saasplatform_saasservicemgmt_v1beta1/py.typed
google/cloud/saasplatform_saasservicemgmt_v1beta1/services/__init__.py
google/cloud/saasplatform_saasservicemgmt_v1beta1/services/saas_deployments/__init__.py
google/cloud/saasplatform_saasservicemgmt_v1beta1/services/saas_deployments/async_client.py
google/cloud/saasplatform_saasservicemgmt_v1beta1/services/saas_deployments/client.py
google/cloud/saasplatform_saasservicemgmt_v1beta1/services/saas_deployments/pagers.py
google/cloud/saasplatform_saasservicemgmt_v1beta1/services/saas_deployments/transports/__init__.py
google/cloud/saasplatform_saasservicemgmt_v1beta1/services/saas_deployments/transports/base.py
google/cloud/saasplatform_saasservicemgmt_v1beta1/services/saas_deployments/transports/grpc.py
google/cloud/saasplatform_saasservicemgmt_v1beta1/services/saas_deployments/transports/grpc_asyncio.py
google/cloud/saasplatform_saasservicemgmt_v1beta1/services/saas_deployments/transports/rest.py
google/cloud/saasplatform_saasservicemgmt_v1beta1/services/saas_deployments/transports/rest_base.py
google/cloud/saasplatform_saasservicemgmt_v1beta1/services/saas_rollouts/__init__.py
google/cloud/saasplatform_saasservicemgmt_v1beta1/services/saas_rollouts/async_client.py
google/cloud/saasplatform_saasservicemgmt_v1beta1/services/saas_rollouts/client.py
google/cloud/saasplatform_saasservicemgmt_v1beta1/services/saas_rollouts/pagers.py
google/cloud/saasplatform_saasservicemgmt_v1beta1/services/saas_rollouts/transports/__init__.py
google/cloud/saasplatform_saasservicemgmt_v1beta1/services/saas_rollouts/transports/base.py
google_cloud_saasplatform_saasservicemgmt-0.3.0.dist-info/licenses/LICENSE
google_cloud_saasplatform_saasservicemgmt-0.3.0.dist-info/METADATA
google_cloud_saasplatform_saasservicemgmt-0.3.0.dist-info/WHEEL
google_cloud_saasplatform_saasservicemgmt-0.3.0.dist-info/top_level.txt
google_cloud_saasplatform_saasservicemgmt-0.3.0.dist-info/RECORD
